Workbook

Sheet Dashboard
A1: ZulfiQode — Black Iron Quantum AI
A2: 3-Year Financial Model Dashboard | Currency: PKR (USD reference in Assumptions)
A4: KEY METRICS
A5: Total 3-Yr Revenue (PKR) | B5: Total 3-Yr Net Profit (PKR) | C5: Ending Cash, Month 36 (PKR) | D5: Breakeven Month # | E5: Lowest Cash Point (PKR) | F5: Corporate Clients, Yr 3 end | G5: SaaS Subscribers, Yr 3 end
A6: =SUM('Income Statement'!B8:AK8) -> 324980000 | B6: =SUM('Income Statement'!B22:AK22) -> 1.3118713e+08 | C6: ='Cashflow Statement'!AK25 -> 1.1262363e+08 | D6: =COUNTIF('Income Statement'!B20:AK20,"<=0")+1 -> 10 | E6: =MIN('Cashflow Statement'!B25:AK25) -> 298667.22 | F6: =Assumptions!AK13 -> 18 | G6: =Assumptions!AK19 -> 300
A9: ANNUAL SUMMARY
A10: Metric | B10: Year 1 | C10: Year 2 | D10: Year 3
A11: Revenue (PKR) | B11: =SUM('Income Statement'!B8:M8) -> 16000000 | C11: =SUM('Income Statement'!N8:Y8) -> 68150000 | D11: =SUM('Income Statement'!Z8:AK8) -> 240830000
A12: COGS (PKR) | B12: =SUM('Income Statement'!B9:M9) -> 1200000 | C12: =SUM('Income Statement'!N9:Y9) -> 4402500 | D12: =SUM('Income Statement'!Z9:AK9) -> 13883625
A13: Gross Profit (PKR) | B13: =SUM('Income Statement'!B10:M10) -> 14800000 | C13: =SUM('Income Statement'!N10:Y10) -> 63747500 | D13: =SUM('Income Statement'!Z10:AK10) -> 226946375
A14: Total OpEx (PKR) | B14: =SUM('Income Statement'!B18:M18) -> 18733333 | C14: =SUM('Income Statement'!N18:Y18) -> 35367333 | D14: =SUM('Income Statement'!Z18:AK18) -> 64743733
A15: Net Profit (PKR) | B15: =SUM('Income Statement'!B22:M22) -> -4126666.7 | C15: =SUM('Income Statement'!N22:Y22) -> 20149918 | D15: =SUM('Income Statement'!Z22:AK22) -> 1.1516388e+08
A16: Ending Cash (PKR) | B16: ='Cashflow Statement'!M25 -> 1906666.7 | C16: ='Cashflow Statement'!Y25 -> 16183252 | D16: ='Cashflow Statement'!AK25 -> 1.1262363e+08
A17: Corporate Clients (end of year) | B17: =Assumptions!M13 -> 3 | C17: =Assumptions!Y13 -> 8 | D17: =Assumptions!AK13 -> 18
A18: SaaS Subscribers (end of year) | B18: =Assumptions!M19 -> 0 | C18: =Assumptions!Y19 -> 60 | D18: =Assumptions!AK19 -> 300
A21: TRENDS

Sheet Assumptions
A1: ZulfiQode — Black Iron Quantum AI | 3-Year Monthly Financial Model
A2: Assumptions tab — Step 1: Revenue Drivers (currency: PKR, with USD reference). Cost drivers added in Step 2.
A3: Legend: Blue text = input, edit freely | Black text = formula, do not overtype | Yellow fill = key assumption to review
A5: Year | B5: 1 | C5: 1 | D5: 1 | E5: 1 | F5: 1 | G5: 1 | H5: 1 | I5: 1 | J5: 1 | K5: 1 | L5: 1 | M5: 1 | N5: 2 | O5: 2 | P5: 2 | Q5: 2 | R5: 2 | S5: 2 | T5: 2 | U5: 2 | V5: 2 | W5: 2 | X5: 2 | Y5: 2 | Z5: 3 | AA5: 3 | AB5: 3 | AC5: 3 | AD5: 3 | AE5: 3 | AF5: 3 | AG5: 3 | AH5: 3 | AI5: 3 | AJ5: 3 | AK5: 3
A6: Month # | B6: 1 | C6: 2 | D6: 3 | E6: 4 | F6: 5 | G6: 6 | H6: 7 | I6: 8 | J6: 9 | K6: 10 | L6: 11 | M6: 12 | N6: 13 | O6: 14 | P6: 15 | Q6: 16 | R6: 17 | S6: 18 | T6: 19 | U6: 20 | V6: 21 | W6: 22 | X6: 23 | Y6: 24 | Z6: 25 | AA6: 26 | AB6: 27 | AC6: 28 | AD6: 29 | AE6: 30 | AF6: 31 | AG6: 32 | AH6: 33 | AI6: 34 | AJ6: 35 | AK6: 36
A9: PKR / USD exchange rate (reference) | B9: 280 | C9: 280 | D9: 280 | E9: 280 | F9: 280 | G9: 280 | H9: 280 | I9: 280 | J9: 280 | K9: 280 | L9: 280 | M9: 280 | N9: 280 | O9: 280 | P9: 280 | Q9: 280 | R9: 280 | S9: 280 | T9: 280 | U9: 280 | V9: 280 | W9: 280 | X9: 280 | Y9: 280 | Z9: 280 | AA9: 280 | AB9: 280 | AC9: 280 | AD9: 280 | AE9: 280 | AF9: 280 | AG9: 280 | AH9: 280 | AI9: 280 | AJ9: 280 | AK9: 280
A11: REVENUE DRIVERS — CORPORATE (ENTERPRISE) CLIENTS
A12: New corporate clients signed this month (input) | B12: 1 | C12: 0 | D12: 0 | E12: 1 | F12: 0 | G12: 0 | H12: 0 | I12: 0 | J12: 0 | K12: 1 | L12: 0 | M12: 0 | N12: 1 | O12: 0 | P12: 0 | Q12: 1 | R12: 0 | S12: 0 | T12: 1 | U12: 0 | V12: 0 | W12: 2 | X12: 0 | Y12: 0 | Z12: 2 | AA12: 0 | AB12: 0 | AC12: 2 | AD12: 0 | AE12: 0 | AF12: 3 | AG12: 0 | AH12: 0 | AI12: 3 | AJ12: 0 | AK12: 0
A13: Cumulative corporate clients (formula) | B13: =B12 -> 1 | C13: =B13+C12 -> 1 | D13: =C13+D12 -> 1 | E13: =D13+E12 -> 2 | F13: =E13+F12 -> 2 | G13: =F13+G12 -> 2 | H13: =G13+H12 -> 2 | I13: =H13+I12 -> 2 | J13: =I13+J12 -> 2 | ... AK13: =AJ13+AK12 -> 18
A14: Annual Contract Value per corporate client, PKR (input) | B14: 8000000 | C14: 8000000 | D14: 8000000 | E14: 8000000 | F14: 8000000 | G14: 8000000 | H14: 8000000 | I14: 8000000 | J14: 8000000 | K14: 8000000 | L14: 8000000 | M14: 8000000 | N14: 8800000 | O14: 8800000 | P14: 8800000 | Q14: 8800000 | R14: 8800000 | S14: 8800000 | T14: 8800000 | U14: 8800000 | V14: 8800000 | W14: 8800000 | X14: 8800000 | Y14: 8800000 | Z14: 9680000 | AA14: 9680000 | AB14: 9680000 | AC14: 9680000 | AD14: 9680000 | AE14: 9680000 | AF14: 9680000 | AG14: 9680000 | AH14: 9680000 | AI14: 9680000 | AJ14: 9680000 | AK14: 9680000
A15: Corporate revenue this month, PKR (formula) = cumulative clients × ACV ÷ 12 | B15: =B13*B14/12 -> 666666.67 | C15: =C13*C14/12 -> 666666.67 | D15: =D13*D14/12 -> 666666.67 | E15: =E13*E14/12 -> 1333333.3 | F15: =F13*F14/12 -> 1333333.3 | G15: =G13*G14/12 -> 1333333.3 | H15: =H13*H14/12 -> 1333333.3 | I15: =I13*I14/12 -> 1333333.3 | ... AK15: =AK13*AK14/12 -> 14520000
A17: REVENUE DRIVERS — SAAS SUBSCRIBERS (launches Year 2)
A18: New subscribers this month (input) | B18: 0 | C18: 0 | D18: 0 | E18: 0 | F18: 0 | G18: 0 | H18: 0 | I18: 0 | J18: 0 | K18: 0 | L18: 0 | M18: 0 | N18: 5 | O18: 5 | P18: 5 | Q18: 5 | R18: 5 | S18: 5 | T18: 5 | U18: 5 | V18: 5 | W18: 5 | X18: 5 | Y18: 5 | Z18: 20 | AA18: 20 | AB18: 20 | AC18: 20 | AD18: 20 | AE18: 20 | AF18: 20 | AG18: 20 | AH18: 20 | AI18: 20 | AJ18: 20 | AK18: 20
A19: Cumulative subscribers (formula) | B19: =B18 -> 0 | C19: =B19+C18 -> 0 | D19: =C19+D18 -> 0 | E19: =D19+E18 -> 0 | F19: =E19+F18 -> 0 | G19: =F19+G18 -> 0 | H19: =G19+H18 -> 0 | I19: =H19+I18 -> 0 | J19: =I19+J18 -> 0 | ... AK19: =AJ19+AK18 -> 300
A20: Subscription price per month, PKR (input) | B20: 0 | C20: 0 | D20: 0 | E20: 0 | F20: 0 | G20: 0 | H20: 0 | I20: 0 | J20: 0 | K20: 0 | L20: 0 | M20: 0 | N20: 45000 | O20: 45000 | P20: 45000 | Q20: 45000 | R20: 45000 | S20: 45000 | T20: 45000 | U20: 45000 | V20: 45000 | W20: 45000 | X20: 45000 | Y20: 45000 | Z20: 47250 | AA20: 47250 | AB20: 47250 | AC20: 47250 | AD20: 47250 | AE20: 47250 | AF20: 47250 | AG20: 47250 | AH20: 47250 | AI20: 47250 | AJ20: 47250 | AK20: 47250
A21: SaaS revenue this month, PKR (formula) = cumulative subscribers × price | B21: =B19*B20 -> 0 | C21: =C19*C20 -> 0 | D21: =D19*D20 -> 0 | E21: =E19*E20 -> 0 | F21: =F19*F20 -> 0 | G21: =G19*G20 -> 0 | H21: =H19*H20 -> 0 | I21: =I19*I20 -> 0 | ... AK21: =AK19*AK20 -> 14175000
A23: TOTAL REVENUE
A24: Total revenue this month, PKR (formula) | B24: =B15+B21 -> 666666.67 | C24: =C15+C21 -> 666666.67 | D24: =D15+D21 -> 666666.67 | E24: =E15+E21 -> 1333333.3 | F24: =F15+F21 -> 1333333.3 | G24: =G15+G21 -> 1333333.3 | H24: =H15+H21 -> 1333333.3 | I24: =I15+I21 -> 1333333.3 | ... AK24: =AK15+AK21 -> 28695000
A25: Total revenue this month, USD reference (formula) | B25: =B24/B9 -> 2380.9524 | C25: =C24/C9 -> 2380.9524 | D25: =D24/D9 -> 2380.9524 | E25: =E24/E9 -> 4761.9048 | F25: =F24/F9 -> 4761.9048 | G25: =G24/G9 -> 4761.9048 | H25: =H24/H9 -> 4761.9048 | I25: =I24/I9 -> 4761.9048 | ... AK25: =AK24/AK9 -> 102482.14
A27: COLLECTIONS ASSUMPTION
A28: Bad debt % of corporate revenue (input) | B28: 0.02 | C28: 0.02 | D28: 0.02 | E28: 0.02 | F28: 0.02 | G28: 0.02 | H28: 0.02 | I28: 0.02 | J28: 0.02 | K28: 0.02 | L28: 0.02 | M28: 0.02 | N28: 0.02 | O28: 0.02 | P28: 0.02 | Q28: 0.02 | R28: 0.02 | S28: 0.02 | T28: 0.02 | U28: 0.02 | V28: 0.02 | W28: 0.02 | X28: 0.02 | Y28: 0.02 | Z28: 0.02 | AA28: 0.02 | AB28: 0.02 | AC28: 0.02 | AD28: 0.02 | AE28: 0.02 | AF28: 0.02 | AG28: 0.02 | AH28: 0.02 | AI28: 0.02 | AJ28: 0.02 | AK28: 0.02
A29: Bad debt amount, PKR (formula, reference — used in Step 4 Income Statement) | B29: =B15*B28 -> 13333.333 | C29: =C15*C28 -> 13333.333 | D29: =D15*D28 -> 13333.333 | E29: =E15*E28 -> 26666.667 | F29: =F15*F28 -> 26666.667 | G29: =G15*G28 -> 26666.667 | H29: =H15*H28 -> 26666.667 | I29: =I15*I28 -> 26666.667 | ... AK29: =AK15*AK28 -> 290400
A31: COST DRIVERS — COGS (data feeds, compute, hosting)
A32: Infra & market-data cost per corporate client / month, PKR (input) | B32: 50000 | C32: 50000 | D32: 50000 | E32: 50000 | F32: 50000 | G32: 50000 | H32: 50000 | I32: 50000 | J32: 50000 | K32: 50000 | L32: 50000 | M32: 50000 | N32: 52500 | O32: 52500 | P32: 52500 | Q32: 52500 | R32: 52500 | S32: 52500 | T32: 52500 | U32: 52500 | V32: 52500 | W32: 52500 | X32: 52500 | Y32: 52500 | Z32: 55125 | AA32: 55125 | AB32: 55125 | AC32: 55125 | AD32: 55125 | AE32: 55125 | AF32: 55125 | AG32: 55125 | AH32: 55125 | AI32: 55125 | AJ32: 55125 | AK32: 55125
A33: Infra cost — corporate clients, PKR (formula) | B33: =B13*B32 -> 50000 | C33: =C13*C32 -> 50000 | D33: =D13*D32 -> 50000 | E33: =E13*E32 -> 100000 | F33: =F13*F32 -> 100000 | G33: =G13*G32 -> 100000 | H33: =H13*H32 -> 100000 | I33: =I13*I32 -> 100000 | ... AK33: =AK13*AK32 -> 992250
A34: Hosting/support cost per SaaS subscriber / month, PKR (input) | B34: 2000 | C34: 2000 | D34: 2000 | E34: 2000 | F34: 2000 | G34: 2000 | H34: 2000 | I34: 2000 | J34: 2000 | K34: 2000 | L34: 2000 | M34: 2000 | N34: 2000 | O34: 2000 | P34: 2000 | Q34: 2000 | R34: 2000 | S34: 2000 | T34: 2000 | U34: 2000 | V34: 2000 | W34: 2000 | X34: 2000 | Y34: 2000 | Z34: 2100 | AA34: 2100 | AB34: 2100 | AC34: 2100 | AD34: 2100 | AE34: 2100 | AF34: 2100 | AG34: 2100 | AH34: 2100 | AI34: 2100 | AJ34: 2100 | AK34: 2100
A35: Hosting cost — SaaS subscribers, PKR (formula) | B35: =B19*B34 -> 0 | C35: =C19*C34 -> 0 | D35: =D19*D34 -> 0 | E35: =E19*E34 -> 0 | F35: =F19*F34 -> 0 | G35: =G19*G34 -> 0 | H35: =H19*H34 -> 0 | I35: =I19*I34 -> 0 | ... AK35: =AK19*AK34 -> 630000
A36: Total COGS this month, PKR (formula) | B36: =B33+B35 -> 50000 | C36: =C33+C35 -> 50000 | D36: =D33+D35 -> 50000 | E36: =E33+E35 -> 100000 | F36: =F33+F35 -> 100000 | G36: =G33+G35 -> 100000 | H36: =H33+H35 -> 100000 | I36: =I33+I35 -> 100000 | ... AK36: =AK33+AK35 -> 1622250
A38: COST DRIVERS — OPERATING EXPENSES
A39: Marketing expense, % of total revenue (input) | B39: 0.08 | C39: 0.08 | D39: 0.08 | E39: 0.08 | F39: 0.08 | G39: 0.08 | H39: 0.08 | I39: 0.08 | J39: 0.08 | K39: 0.08 | L39: 0.08 | M39: 0.08 | N39: 0.08 | O39: 0.08 | P39: 0.08 | Q39: 0.08 | R39: 0.08 | S39: 0.08 | T39: 0.08 | U39: 0.08 | V39: 0.08 | W39: 0.08 | X39: 0.08 | Y39: 0.08 | Z39: 0.08 | AA39: 0.08 | AB39: 0.08 | AC39: 0.08 | AD39: 0.08 | AE39: 0.08 | AF39: 0.08 | AG39: 0.08 | AH39: 0.08 | AI39: 0.08 | AJ39: 0.08 | AK39: 0.08
A40: Marketing expense, PKR (formula) | B40: =B24*B39 -> 53333.333 | C40: =C24*C39 -> 53333.333 | D40: =D24*D39 -> 53333.333 | E40: =E24*E39 -> 106666.67 | F40: =F24*F39 -> 106666.67 | G40: =G24*G39 -> 106666.67 | H40: =H24*H39 -> 106666.67 | I40: =I24*I39 -> 106666.67 | ... AK40: =AK24*AK39 -> 2295600
A41: General & administrative expense, PKR / month (input) | B41: 300000 | C41: 300000 | D41: 300000 | E41: 300000 | F41: 300000 | G41: 300000 | H41: 300000 | I41: 300000 | J41: 300000 | K41: 300000 | L41: 300000 | M41: 300000 | N41: 330000 | O41: 330000 | P41: 330000 | Q41: 330000 | R41: 330000 | S41: 330000 | T41: 330000 | U41: 330000 | V41: 330000 | W41: 330000 | X41: 330000 | Y41: 330000 | Z41: 363000 | AA41: 363000 | AB41: 363000 | AC41: 363000 | AD41: 363000 | AE41: 363000 | AF41: 363000 | AG41: 363000 | AH41: 363000 | AI41: 363000 | AJ41: 363000 | AK41: 363000
A43: TAX ASSUMPTION
A44: Corporate income tax rate, Pakistan (input) — applied only when profitable | B44: 0.29 | C44: 0.29 | D44: 0.29 | E44: 0.29 | F44: 0.29 | G44: 0.29 | H44: 0.29 | I44: 0.29 | J44: 0.29 | K44: 0.29 | L44: 0.29 | M44: 0.29 | N44: 0.29 | O44: 0.29 | P44: 0.29 | Q44: 0.29 | R44: 0.29 | S44: 0.29 | T44: 0.29 | U44: 0.29 | V44: 0.29 | W44: 0.29 | X44: 0.29 | Y44: 0.29 | Z44: 0.29 | AA44: 0.29 | AB44: 0.29 | AC44: 0.29 | AD44: 0.29 | AE44: 0.29 | AF44: 0.29 | AG44: 0.29 | AH44: 0.29 | AI44: 0.29 | AJ44: 0.29 | AK44: 0.29
A46: WORKING CAPITAL ASSUMPTIONS
A47: Days Sales Outstanding — Accounts Receivable (input) | B47: 30 | C47: 30 | D47: 30 | E47: 30 | F47: 30 | G47: 30 | H47: 30 | I47: 30 | J47: 30 | K47: 30 | L47: 30 | M47: 30 | N47: 30 | O47: 30 | P47: 30 | Q47: 30 | R47: 30 | S47: 30 | T47: 30 | U47: 30 | V47: 30 | W47: 30 | X47: 30 | Y47: 30 | Z47: 30 | AA47: 30 | AB47: 30 | AC47: 30 | AD47: 30 | AE47: 30 | AF47: 30 | AG47: 30 | AH47: 30 | AI47: 30 | AJ47: 30 | AK47: 30
A48: Days Payable Outstanding — Accounts Payable (input) | B48: 20 | C48: 20 | D48: 20 | E48: 20 | F48: 20 | G48: 20 | H48: 20 | I48: 20 | J48: 20 | K48: 20 | L48: 20 | M48: 20 | N48: 20 | O48: 20 | P48: 20 | Q48: 20 | R48: 20 | S48: 20 | T48: 20 | U48: 20 | V48: 20 | W48: 20 | X48: 20 | Y48: 20 | Z48: 20 | AA48: 20 | AB48: 20 | AC48: 20 | AD48: 20 | AE48: 20 | AF48: 20 | AG48: 20 | AH48: 20 | AI48: 20 | AJ48: 20 | AK48: 20

Sheet Salary
A1: ZulfiQode — Team & Salary Schedule (Step 2)
A2: Headcount is an input (blue). Salary per role is an input (blue). Totals are formulas (black).
A4: Year | B4: 1 | C4: 1 | D4: 1 | E4: 1 | F4: 1 | G4: 1 | H4: 1 | I4: 1 | J4: 1 | K4: 1 | L4: 1 | M4: 1 | N4: 2 | O4: 2 | P4: 2 | Q4: 2 | R4: 2 | S4: 2 | T4: 2 | U4: 2 | V4: 2 | W4: 2 | X4: 2 | Y4: 2 | Z4: 3 | AA4: 3 | AB4: 3 | AC4: 3 | AD4: 3 | AE4: 3 | AF4: 3 | AG4: 3 | AH4: 3 | AI4: 3 | AJ4: 3 | AK4: 3
A5: Month # | B5: 1 | C5: 2 | D5: 3 | E5: 4 | F5: 5 | G5: 6 | H5: 7 | I5: 8 | J5: 9 | K5: 10 | L5: 11 | M5: 12 | N5: 13 | O5: 14 | P5: 15 | Q5: 16 | R5: 17 | S5: 18 | T5: 19 | U5: 20 | V5: 21 | W5: 22 | X5: 23 | Y5: 24 | Z5: 25 | AA5: 26 | AB5: 27 | AC5: 28 | AD5: 29 | AE5: 30 | AF5: 31 | AG5: 32 | AH5: 33 | AI5: 34 | AJ5: 35 | AK5: 36
A7: HEADCOUNT (input)
A8: Founder / CEO | B8: 1 | C8: 1 | D8: 1 | E8: 1 | F8: 1 | G8: 1 | H8: 1 | I8: 1 | J8: 1 | K8: 1 | L8: 1 | M8: 1 | N8: 1 | O8: 1 | P8: 1 | Q8: 1 | R8: 1 | S8: 1 | T8: 1 | U8: 1 | V8: 1 | W8: 1 | X8: 1 | Y8: 1 | Z8: 1 | AA8: 1 | AB8: 1 | AC8: 1 | AD8: 1 | AE8: 1 | AF8: 1 | AG8: 1 | AH8: 1 | AI8: 1 | AJ8: 1 | AK8: 1
A9: Quant / AI Engineer | B9: 1 | C9: 1 | D9: 1 | E9: 1 | F9: 1 | G9: 1 | H9: 1 | I9: 1 | J9: 1 | K9: 1 | L9: 1 | M9: 1 | N9: 2 | O9: 2 | P9: 2 | Q9: 2 | R9: 2 | S9: 2 | T9: 2 | U9: 2 | V9: 2 | W9: 2 | X9: 2 | Y9: 2 | Z9: 3 | AA9: 3 | AB9: 3 | AC9: 3 | AD9: 3 | AE9: 3 | AF9: 3 | AG9: 3 | AH9: 3 | AI9: 3 | AJ9: 3 | AK9: 3
A10: Backend / Data Engineer | B10: 1 | C10: 1 | D10: 1 | E10: 1 | F10: 1 | G10: 1 | H10: 1 | I10: 1 | J10: 1 | K10: 1 | L10: 1 | M10: 1 | N10: 2 | O10: 2 | P10: 2 | Q10: 2 | R10: 2 | S10: 2 | T10: 2 | U10: 2 | V10: 2 | W10: 2 | X10: 2 | Y10: 2 | Z10: 3 | AA10: 3 | AB10: 3 | AC10: 3 | AD10: 3 | AE10: 3 | AF10: 3 | AG10: 3 | AH10: 3 | AI10: 3 | AJ10: 3 | AK10: 3
A11: Sales & BD Lead | B11: 0 | C11: 0 | D11: 0 | E11: 0 | F11: 0 | G11: 0 | H11: 0 | I11: 0 | J11: 0 | K11: 0 | L11: 0 | M11: 0 | N11: 1 | O11: 1 | P11: 1 | Q11: 1 | R11: 1 | S11: 1 | T11: 1 | U11: 1 | V11: 1 | W11: 1 | X11: 1 | Y11: 1 | Z11: 2 | AA11: 2 | AB11: 2 | AC11: 2 | AD11: 2 | AE11: 2 | AF11: 2 | AG11: 2 | AH11: 2 | AI11: 2 | AJ11: 2 | AK11: 2
A12: Ops / Admin | B12: 1 | C12: 1 | D12: 1 | E12: 1 | F12: 1 | G12: 1 | H12: 1 | I12: 1 | J12: 1 | K12: 1 | L12: 1 | M12: 1 | N12: 1 | O12: 1 | P12: 1 | Q12: 1 | R12: 1 | S12: 1 | T12: 1 | U12: 1 | V12: 1 | W12: 1 | X12: 1 | Y12: 1 | Z12: 1 | AA12: 1 | AB12: 1 | AC12: 1 | AD12: 1 | AE12: 1 | AF12: 1 | AG12: 1 | AH12: 1 | AI12: 1 | AJ12: 1 | AK12: 1
A14: SALARY PER PERSON / MONTH, PKR (input)
A15: Founder / CEO | B15: 400000 | C15: 400000 | D15: 400000 | E15: 400000 | F15: 400000 | G15: 400000 | H15: 400000 | I15: 400000 | J15: 400000 | K15: 400000 | L15: 400000 | M15: 400000 | N15: 440000 | O15: 440000 | P15: 440000 | Q15: 440000 | R15: 440000 | S15: 440000 | T15: 440000 | U15: 440000 | V15: 440000 | W15: 440000 | X15: 440000 | Y15: 440000 | Z15: 484000 | AA15: 484000 | AB15: 484000 | AC15: 484000 | AD15: 484000 | AE15: 484000 | AF15: 484000 | AG15: 484000 | AH15: 484000 | AI15: 484000 | AJ15: 484000 | AK15: 484000
A16: Quant / AI Engineer | B16: 300000 | C16: 300000 | D16: 300000 | E16: 300000 | F16: 300000 | G16: 300000 | H16: 300000 | I16: 300000 | J16: 300000 | K16: 300000 | L16: 300000 | M16: 300000 | N16: 330000 | O16: 330000 | P16: 330000 | Q16: 330000 | R16: 330000 | S16: 330000 | T16: 330000 | U16: 330000 | V16: 330000 | W16: 330000 | X16: 330000 | Y16: 330000 | Z16: 363000 | AA16: 363000 | AB16: 363000 | AC16: 363000 | AD16: 363000 | AE16: 363000 | AF16: 363000 | AG16: 363000 | AH16: 363000 | AI16: 363000 | AJ16: 363000 | AK16: 363000
A17: Backend / Data Engineer | B17: 250000 | C17: 250000 | D17: 250000 | E17: 250000 | F17: 250000 | G17: 250000 | H17: 250000 | I17: 250000 | J17: 250000 | K17: 250000 | L17: 250000 | M17: 250000 | N17: 275000 | O17: 275000 | P17: 275000 | Q17: 275000 | R17: 275000 | S17: 275000 | T17: 275000 | U17: 275000 | V17: 275000 | W17: 275000 | X17: 275000 | Y17: 275000 | Z17: 302500 | AA17: 302500 | AB17: 302500 | AC17: 302500 | AD17: 302500 | AE17: 302500 | AF17: 302500 | AG17: 302500 | AH17: 302500 | AI17: 302500 | AJ17: 302500 | AK17: 302500
A18: Sales & BD Lead | B18: 200000 | C18: 200000 | D18: 200000 | E18: 200000 | F18: 200000 | G18: 200000 | H18: 200000 | I18: 200000 | J18: 200000 | K18: 200000 | L18: 200000 | M18: 200000 | N18: 220000 | O18: 220000 | P18: 220000 | Q18: 220000 | R18: 220000 | S18: 220000 | T18: 220000 | U18: 220000 | V18: 220000 | W18: 220000 | X18: 220000 | Y18: 220000 | Z18: 242000 | AA18: 242000 | AB18: 242000 | AC18: 242000 | AD18: 242000 | AE18: 242000 | AF18: 242000 | AG18: 242000 | AH18: 242000 | AI18: 242000 | AJ18: 242000 | AK18: 242000
A19: Ops / Admin | B19: 100000 | C19: 100000 | D19: 100000 | E19: 100000 | F19: 100000 | G19: 100000 | H19: 100000 | I19: 100000 | J19: 100000 | K19: 100000 | L19: 100000 | M19: 100000 | N19: 110000 | O19: 110000 | P19: 110000 | Q19: 110000 | R19: 110000 | S19: 110000 | T19: 110000 | U19: 110000 | V19: 110000 | W19: 110000 | X19: 110000 | Y19: 110000 | Z19: 121000 | AA19: 121000 | AB19: 121000 | AC19: 121000 | AD19: 121000 | AE19: 121000 | AF19: 121000 | AG19: 121000 | AH19: 121000 | AI19: 121000 | AJ19: 121000 | AK19: 121000
A21: TOTAL SALARY EXPENSE BY ROLE, PKR (formula)
A22: Founder / CEO | B22: =B8*B15 -> 400000 | C22: =C8*C15 -> 400000 | D22: =D8*D15 -> 400000 | E22: =E8*E15 -> 400000 | F22: =F8*F15 -> 400000 | G22: =G8*G15 -> 400000 | H22: =H8*H15 -> 400000 | I22: =I8*I15 -> 400000 | ... AK22: =AK8*AK15 -> 484000
A23: Quant / AI Engineer | B23: =B9*B16 -> 300000 | C23: =C9*C16 -> 300000 | D23: =D9*D16 -> 300000 | E23: =E9*E16 -> 300000 | F23: =F9*F16 -> 300000 | G23: =G9*G16 -> 300000 | H23: =H9*H16 -> 300000 | I23: =I9*I16 -> 300000 | ... AK23: =AK9*AK16 -> 1089000
A24: Backend / Data Engineer | B24: =B10*B17 -> 250000 | C24: =C10*C17 -> 250000 | D24: =D10*D17 -> 250000 | E24: =E10*E17 -> 250000 | F24: =F10*F17 -> 250000 | G24: =G10*G17 -> 250000 | H24: =H10*H17 -> 250000 | I24: =I10*I17 -> 250000 | ... AK24: =AK10*AK17 -> 907500
A25: Sales & BD Lead | B25: =B11*B18 -> 0 | C25: =C11*C18 -> 0 | D25: =D11*D18 -> 0 | E25: =E11*E18 -> 0 | F25: =F11*F18 -> 0 | G25: =G11*G18 -> 0 | H25: =H11*H18 -> 0 | I25: =I11*I18 -> 0 | ... AK25: =AK11*AK18 -> 484000
A26: Ops / Admin | B26: =B12*B19 -> 100000 | C26: =C12*C19 -> 100000 | D26: =D12*D19 -> 100000 | E26: =E12*E19 -> 100000 | F26: =F12*F19 -> 100000 | G26: =G12*G19 -> 100000 | H26: =H12*H19 -> 100000 | I26: =I12*I19 -> 100000 | ... AK26: =AK12*AK19 -> 121000
A28: TOTAL SALARY EXPENSE, PKR (formula) | B28: =SUM(B22:B26) -> 1050000 | C28: =SUM(C22:C26) -> 1050000 | D28: =SUM(D22:D26) -> 1050000 | E28: =SUM(E22:E26) -> 1050000 | F28: =SUM(F22:F26) -> 1050000 | G28: =SUM(G22:G26) -> 1050000 | H28: =SUM(H22:H26) -> 1050000 | I28: =SUM(I22:I26) -> 1050000 | ... AK28: =SUM(AK22:AK26) -> 3085500

Sheet Depreciation
A1: ZulfiQode — Depreciation & Capex Schedule (Step 3)
A2: Asset register (top) drives the monthly depreciation schedule (below) via formulas.
A3: Legend: Blue text = input | Black text = formula | Yellow fill = key assumption
A5: Asset | B5: Purchase Month # | C5: Purchase Price, PKR | D5: Useful Life, months | E5: Monthly Depreciation, PKR
A6: Laptops & Equipment — Year 1 team (4 units) | B6: 1 | C6: 1000000 | D6: 36 | E6: =C6/D6 -> 27777.778
A7: GPU / AI Workstation | B7: 1 | C7: 1500000 | D7: 36 | E7: =C7/D7 -> 41666.667
A8: Office Setup & Furniture | B8: 1 | C8: 500000 | D8: 60 | E8: =C8/D8 -> 8333.3333
A9: Laptops & Equipment — Year 2 additions (3 units) | B9: 13 | C9: 750000 | D9: 36 | E9: =C9/D9 -> 20833.333
A10: Laptops & Equipment — Year 3 additions (3 units) | B10: 25 | C10: 750000 | D10: 36 | E10: =C10/D10 -> 20833.333
A11: Total | C11: =SUM(C6:C10) -> 4500000 | E11: =SUM(E6:E10) -> 119444.44
A14: Year | B14: 1 | C14: 1 | D14: 1 | E14: 1 | F14: 1 | G14: 1 | H14: 1 | I14: 1 | J14: 1 | K14: 1 | L14: 1 | M14: 1 | N14: 2 | O14: 2 | P14: 2 | Q14: 2 | R14: 2 | S14: 2 | T14: 2 | U14: 2 | V14: 2 | W14: 2 | X14: 2 | Y14: 2 | Z14: 3 | AA14: 3 | AB14: 3 | AC14: 3 | AD14: 3 | AE14: 3 | AF14: 3 | AG14: 3 | AH14: 3 | AI14: 3 | AJ14: 3 | AK14: 3
A15: Month # | B15: 1 | C15: 2 | D15: 3 | E15: 4 | F15: 5 | G15: 6 | H15: 7 | I15: 8 | J15: 9 | K15: 10 | L15: 11 | M15: 12 | N15: 13 | O15: 14 | P15: 15 | Q15: 16 | R15: 17 | S15: 18 | T15: 19 | U15: 20 | V15: 21 | W15: 22 | X15: 23 | Y15: 24 | Z15: 25 | AA15: 26 | AB15: 27 | AC15: 28 | AD15: 29 | AE15: 30 | AF15: 31 | AG15: 32 | AH15: 33 | AI15: 34 | AJ15: 35 | AK15: 36
A16: MONTHLY DEPRECIATION BY ASSET (formula)
A17: Laptops & Equipment — Year 1 team (4 units) | B17: =IF(AND(B15>=$B$6,B15<$B$6+$D$6),$E$6,0) -> 27777.778 | C17: =IF(AND(C15>=$B$6,C15<$B$6+$D$6),$E$6,0) -> 27777.778 | D17: =IF(AND(D15>=$B$6,D15<$B$6+$D$6),$E$6,0) -> 27777.778 | E17: =IF(AND(E15>=$B$6,E15<$B$6+$D$6),$E$6,0) -> 27777.778 | F17: =IF(AND(F15>=$B$6,F15<$B$6+$D$6),$E$6,0) -> 27777.778 | G17: =IF(AND(G15>=$B$6,G15<$B$6+$D$6),$E$6,0) -> 27777.778 | H17: =IF(AND(H15>=$B$6,H15<$B$6+$D$6),$E$6,0) -> 27777.778 | I17: =IF(AND(I15>=$B$6,I15<$B$6+$D$6),$E$6,0) -> 27777.778 | ... AK17: =IF(AND(AK15>=$B$6,AK15<$B$6+$D$6),$E$6,0) -> 27777.778
A18: GPU / AI Workstation | B18: =IF(AND(B15>=$B$7,B15<$B$7+$D$7),$E$7,0) -> 41666.667 | C18: =IF(AND(C15>=$B$7,C15<$B$7+$D$7),$E$7,0) -> 41666.667 | D18: =IF(AND(D15>=$B$7,D15<$B$7+$D$7),$E$7,0) -> 41666.667 | E18: =IF(AND(E15>=$B$7,E15<$B$7+$D$7),$E$7,0) -> 41666.667 | F18: =IF(AND(F15>=$B$7,F15<$B$7+$D$7),$E$7,0) -> 41666.667 | G18: =IF(AND(G15>=$B$7,G15<$B$7+$D$7),$E$7,0) -> 41666.667 | H18: =IF(AND(H15>=$B$7,H15<$B$7+$D$7),$E$7,0) -> 41666.667 | I18: =IF(AND(I15>=$B$7,I15<$B$7+$D$7),$E$7,0) -> 41666.667 | ... AK18: =IF(AND(AK15>=$B$7,AK15<$B$7+$D$7),$E$7,0) -> 41666.667
A19: Office Setup & Furniture | B19: =IF(AND(B15>=$B$8,B15<$B$8+$D$8),$E$8,0) -> 8333.3333 | C19: =IF(AND(C15>=$B$8,C15<$B$8+$D$8),$E$8,0) -> 8333.3333 | D19: =IF(AND(D15>=$B$8,D15<$B$8+$D$8),$E$8,0) -> 8333.3333 | E19: =IF(AND(E15>=$B$8,E15<$B$8+$D$8),$E$8,0) -> 8333.3333 | F19: =IF(AND(F15>=$B$8,F15<$B$8+$D$8),$E$8,0) -> 8333.3333 | G19: =IF(AND(G15>=$B$8,G15<$B$8+$D$8),$E$8,0) -> 8333.3333 | H19: =IF(AND(H15>=$B$8,H15<$B$8+$D$8),$E$8,0) -> 8333.3333 | I19: =IF(AND(I15>=$B$8,I15<$B$8+$D$8),$E$8,0) -> 8333.3333 | ... AK19: =IF(AND(AK15>=$B$8,AK15<$B$8+$D$8),$E$8,0) -> 8333.3333
A20: Laptops & Equipment — Year 2 additions (3 units) | B20: =IF(AND(B15>=$B$9,B15<$B$9+$D$9),$E$9,0) -> 0 | C20: =IF(AND(C15>=$B$9,C15<$B$9+$D$9),$E$9,0) -> 0 | D20: =IF(AND(D15>=$B$9,D15<$B$9+$D$9),$E$9,0) -> 0 | E20: =IF(AND(E15>=$B$9,E15<$B$9+$D$9),$E$9,0) -> 0 | F20: =IF(AND(F15>=$B$9,F15<$B$9+$D$9),$E$9,0) -> 0 | G20: =IF(AND(G15>=$B$9,G15<$B$9+$D$9),$E$9,0) -> 0 | H20: =IF(AND(H15>=$B$9,H15<$B$9+$D$9),$E$9,0) -> 0 | I20: =IF(AND(I15>=$B$9,I15<$B$9+$D$9),$E$9,0) -> 0 | ... AK20: =IF(AND(AK15>=$B$9,AK15<$B$9+$D$9),$E$9,0) -> 20833.333
A21: Laptops & Equipment — Year 3 additions (3 units) | B21: =IF(AND(B15>=$B$10,B15<$B$10+$D$10),$E$10,0) -> 0 | C21: =IF(AND(C15>=$B$10,C15<$B$10+$D$10),$E$10,0) -> 0 | D21: =IF(AND(D15>=$B$10,D15<$B$10+$D$10),$E$10,0) -> 0 | E21: =IF(AND(E15>=$B$10,E15<$B$10+$D$10),$E$10,0) -> 0 | F21: =IF(AND(F15>=$B$10,F15<$B$10+$D$10),$E$10,0) -> 0 | G21: =IF(AND(G15>=$B$10,G15<$B$10+$D$10),$E$10,0) -> 0 | H21: =IF(AND(H15>=$B$10,H15<$B$10+$D$10),$E$10,0) -> 0 | I21: =IF(AND(I15>=$B$10,I15<$B$10+$D$10),$E$10,0) -> 0 | ... AK21: =IF(AND(AK15>=$B$10,AK15<$B$10+$D$10),$E$10,0) -> 20833.333
A22: Total Depreciation Expense this month, PKR (formula) | B22: =SUM(B17:B21) -> 77777.778 | C22: =SUM(C17:C21) -> 77777.778 | D22: =SUM(D17:D21) -> 77777.778 | E22: =SUM(E17:E21) -> 77777.778 | F22: =SUM(F17:F21) -> 77777.778 | G22: =SUM(G17:G21) -> 77777.778 | H22: =SUM(H17:H21) -> 77777.778 | I22: =SUM(I17:I21) -> 77777.778 | ... AK22: =SUM(AK17:AK21) -> 119444.44
A23: Accumulated Depreciation, PKR (formula) | B23: =B22 -> 77777.778 | C23: =B23+C22 -> 155555.56 | D23: =C23+D22 -> 233333.33 | E23: =D23+E22 -> 311111.11 | F23: =E23+F22 -> 388888.89 | G23: =F23+G22 -> 466666.67 | H23: =G23+H22 -> 544444.44 | I23: =H23+I22 -> 622222.22 | J23: =I23+J22 -> 700000 | ... AK23: =AJ23+AK22 -> 3550000
A24: Net Book Value of Equipment, PKR (formula) = Total Cost − Accumulated Depreciation | B24: =SUMPRODUCT(($B$6:$B$10<=B15)*$C$6:$C$10)-B23 -> 2922222.2 | C24: =SUMPRODUCT(($B$6:$B$10<=C15)*$C$6:$C$10)-C23 -> 2844444.4 | D24: =SUMPRODUCT(($B$6:$B$10<=D15)*$C$6:$C$10)-D23 -> 2766666.7 | E24: =SUMPRODUCT(($B$6:$B$10<=E15)*$C$6:$C$10)-E23 -> 2688888.9 | F24: =SUMPRODUCT(($B$6:$B$10<=F15)*$C$6:$C$10)-F23 -> 2611111.1 | G24: =SUMPRODUCT(($B$6:$B$10<=G15)*$C$6:$C$10)-G23 -> 2533333.3 | H24: =SUMPRODUCT(($B$6:$B$10<=H15)*$C$6:$C$10)-H23 -> 2455555.6 | I24: =SUMPRODUCT(($B$6:$B$10<=I15)*$C$6:$C$10)-I23 -> 2377777.8 | ... AK24: =SUMPRODUCT(($B$6:$B$10<=AK15)*$C$6:$C$10)-AK23 -> 950000

Sheet Income Statement
A1: ZulfiQode — Income Statement (Step 4)
A2: Pulls revenue & cost drivers from Assumptions, payroll from Salary, and depreciation from Depreciation.
A3: Legend: Green text = link to another tab | Black text = formula (same tab) | Bold = subtotal
A5: Year | B5: 1 | C5: 1 | D5: 1 | E5: 1 | F5: 1 | G5: 1 | H5: 1 | I5: 1 | J5: 1 | K5: 1 | L5: 1 | M5: 1 | N5: 2 | O5: 2 | P5: 2 | Q5: 2 | R5: 2 | S5: 2 | T5: 2 | U5: 2 | V5: 2 | W5: 2 | X5: 2 | Y5: 2 | Z5: 3 | AA5: 3 | AB5: 3 | AC5: 3 | AD5: 3 | AE5: 3 | AF5: 3 | AG5: 3 | AH5: 3 | AI5: 3 | AJ5: 3 | AK5: 3
A6: Month # | B6: 1 | C6: 2 | D6: 3 | E6: 4 | F6: 5 | G6: 6 | H6: 7 | I6: 8 | J6: 9 | K6: 10 | L6: 11 | M6: 12 | N6: 13 | O6: 14 | P6: 15 | Q6: 16 | R6: 17 | S6: 18 | T6: 19 | U6: 20 | V6: 21 | W6: 22 | X6: 23 | Y6: 24 | Z6: 25 | AA6: 26 | AB6: 27 | AC6: 28 | AD6: 29 | AE6: 30 | AF6: 31 | AG6: 32 | AH6: 33 | AI6: 34 | AJ6: 35 | AK6: 36
A8: Revenue | B8: =Assumptions!B24 -> 666666.67 | C8: =Assumptions!C24 -> 666666.67 | D8: =Assumptions!D24 -> 666666.67 | E8: =Assumptions!E24 -> 1333333.3 | F8: =Assumptions!F24 -> 1333333.3 | G8: =Assumptions!G24 -> 1333333.3 | H8: =Assumptions!H24 -> 1333333.3 | I8: =Assumptions!I24 -> 1333333.3 | ... AK8: =Assumptions!AK24 -> 28695000
A9: (-) Cost of Revenue (COGS) | B9: =Assumptions!B36 -> 50000 | C9: =Assumptions!C36 -> 50000 | D9: =Assumptions!D36 -> 50000 | E9: =Assumptions!E36 -> 100000 | F9: =Assumptions!F36 -> 100000 | G9: =Assumptions!G36 -> 100000 | H9: =Assumptions!H36 -> 100000 | I9: =Assumptions!I36 -> 100000 | ... AK9: =Assumptions!AK36 -> 1622250
A10: Gross Profit | B10: =B8-B9 -> 616666.67 | C10: =C8-C9 -> 616666.67 | D10: =D8-D9 -> 616666.67 | E10: =E8-E9 -> 1233333.3 | F10: =F8-F9 -> 1233333.3 | G10: =G8-G9 -> 1233333.3 | H10: =H8-H9 -> 1233333.3 | I10: =I8-I9 -> 1233333.3 | ... AK10: =AK8-AK9 -> 27072750
A12: OPERATING EXPENSES
A13: Marketing Expense | B13: =Assumptions!B40 -> 53333.333 | C13: =Assumptions!C40 -> 53333.333 | D13: =Assumptions!D40 -> 53333.333 | E13: =Assumptions!E40 -> 106666.67 | F13: =Assumptions!F40 -> 106666.67 | G13: =Assumptions!G40 -> 106666.67 | H13: =Assumptions!H40 -> 106666.67 | I13: =Assumptions!I40 -> 106666.67 | ... AK13: =Assumptions!AK40 -> 2295600
A14: Salary Expense | B14: =Salary!B28 -> 1050000 | C14: =Salary!C28 -> 1050000 | D14: =Salary!D28 -> 1050000 | E14: =Salary!E28 -> 1050000 | F14: =Salary!F28 -> 1050000 | G14: =Salary!G28 -> 1050000 | H14: =Salary!H28 -> 1050000 | I14: =Salary!I28 -> 1050000 | ... AK14: =Salary!AK28 -> 3085500
A15: General & Administrative Expense | B15: =Assumptions!B41 -> 300000 | C15: =Assumptions!C41 -> 300000 | D15: =Assumptions!D41 -> 300000 | E15: =Assumptions!E41 -> 300000 | F15: =Assumptions!F41 -> 300000 | G15: =Assumptions!G41 -> 300000 | H15: =Assumptions!H41 -> 300000 | I15: =Assumptions!I41 -> 300000 | ... AK15: =Assumptions!AK41 -> 363000
A16: Bad Debts | B16: =Assumptions!B29 -> 13333.333 | C16: =Assumptions!C29 -> 13333.333 | D16: =Assumptions!D29 -> 13333.333 | E16: =Assumptions!E29 -> 26666.667 | F16: =Assumptions!F29 -> 26666.667 | G16: =Assumptions!G29 -> 26666.667 | H16: =Assumptions!H29 -> 26666.667 | I16: =Assumptions!I29 -> 26666.667 | ... AK16: =Assumptions!AK29 -> 290400
A17: Depreciation Expense | B17: =Depreciation!B22 -> 77777.778 | C17: =Depreciation!C22 -> 77777.778 | D17: =Depreciation!D22 -> 77777.778 | E17: =Depreciation!E22 -> 77777.778 | F17: =Depreciation!F22 -> 77777.778 | G17: =Depreciation!G22 -> 77777.778 | H17: =Depreciation!H22 -> 77777.778 | I17: =Depreciation!I22 -> 77777.778 | ... AK17: =Depreciation!AK22 -> 119444.44
A18: Total Operating Expenses | B18: =SUM(B13:B17) -> 1494444.4 | C18: =SUM(C13:C17) -> 1494444.4 | D18: =SUM(D13:D17) -> 1494444.4 | E18: =SUM(E13:E17) -> 1561111.1 | F18: =SUM(F13:F17) -> 1561111.1 | G18: =SUM(G13:G17) -> 1561111.1 | H18: =SUM(H13:H17) -> 1561111.1 | I18: =SUM(I13:I17) -> 1561111.1 | ... AK18: =SUM(AK13:AK17) -> 6153944.4
A20: Profit Before Tax | B20: =B10-B18 -> -877777.78 | C20: =C10-C18 -> -877777.78 | D20: =D10-D18 -> -877777.78 | E20: =E10-E18 -> -327777.78 | F20: =F10-F18 -> -327777.78 | G20: =G10-G18 -> -327777.78 | H20: =H10-H18 -> -327777.78 | I20: =I10-I18 -> -327777.78 | ... AK20: =AK10-AK18 -> 20918806
A21: Tax (applied only when Profit Before Tax > 0) | B21: =IF(B20>0,B20*Assumptions!B44,0) -> 0 | C21: =IF(C20>0,C20*Assumptions!C44,0) -> 0 | D21: =IF(D20>0,D20*Assumptions!D44,0) -> 0 | E21: =IF(E20>0,E20*Assumptions!E44,0) -> 0 | F21: =IF(F20>0,F20*Assumptions!F44,0) -> 0 | G21: =IF(G20>0,G20*Assumptions!G44,0) -> 0 | H21: =IF(H20>0,H20*Assumptions!H44,0) -> 0 | I21: =IF(I20>0,I20*Assumptions!I44,0) -> 0 | ... AK21: =IF(AK20>0,AK20*Assumptions!AK44,0) -> 6066453.6
A22: Profit After Tax (Net Profit) | B22: =B20-B21 -> -877777.78 | C22: =C20-C21 -> -877777.78 | D22: =D20-D21 -> -877777.78 | E22: =E20-E21 -> -327777.78 | F22: =F20-F21 -> -327777.78 | G22: =G20-G21 -> -327777.78 | H22: =H20-H21 -> -327777.78 | I22: =I20-I21 -> -327777.78 | ... AK22: =AK20-AK21 -> 14852352

Sheet Balance Sheet
A1: ZulfiQode — Balance Sheet (Step 5)
A2: Point-in-time snapshot each month. Equipment links from Depreciation; Receivables/Payables from Assumptions.
A3: Point-in-time snapshot each month. Cash links from the Cashflow Statement; Equipment from Depreciation.
A5: Year | B5: 1 | C5: 1 | D5: 1 | E5: 1 | F5: 1 | G5: 1 | H5: 1 | I5: 1 | J5: 1 | K5: 1 | L5: 1 | M5: 1 | N5: 2 | O5: 2 | P5: 2 | Q5: 2 | R5: 2 | S5: 2 | T5: 2 | U5: 2 | V5: 2 | W5: 2 | X5: 2 | Y5: 2 | Z5: 3 | AA5: 3 | AB5: 3 | AC5: 3 | AD5: 3 | AE5: 3 | AF5: 3 | AG5: 3 | AH5: 3 | AI5: 3 | AJ5: 3 | AK5: 3
A6: Month # | B6: 1 | C6: 2 | D6: 3 | E6: 4 | F6: 5 | G6: 6 | H6: 7 | I6: 8 | J6: 9 | K6: 10 | L6: 11 | M6: 12 | N6: 13 | O6: 14 | P6: 15 | Q6: 16 | R6: 17 | S6: 18 | T6: 19 | U6: 20 | V6: 21 | W6: 22 | X6: 23 | Y6: 24 | Z6: 25 | AA6: 26 | AB6: 27 | AC6: 28 | AD6: 29 | AE6: 30 | AF6: 31 | AG6: 32 | AH6: 33 | AI6: 34 | AJ6: 35 | AK6: 36
A8: ASSETS
A9: Cash (placeholder — linked in Step 6) | B9: ='Cashflow Statement'!B25 -> 5566666.7 | C9: ='Cashflow Statement'!C25 -> 4766666.7 | D9: ='Cashflow Statement'!D25 -> 3966666.7 | E9: ='Cashflow Statement'!E25 -> 3083333.3 | F9: ='Cashflow Statement'!F25 -> 2833333.3 | G9: ='Cashflow Statement'!G25 -> 2583333.3 | H9: ='Cashflow Statement'!H25 -> 2333333.3 | I9: ='Cashflow Statement'!I25 -> 2083333.3 | ... AK9: ='Cashflow Statement'!AK25 -> 1.1262363e+08
A10: Accounts Receivable (formula) = Revenue × DSO ÷ 30 | B10: =Assumptions!B24*Assumptions!B47/30 -> 666666.67 | C10: =Assumptions!C24*Assumptions!C47/30 -> 666666.67 | D10: =Assumptions!D24*Assumptions!D47/30 -> 666666.67 | E10: =Assumptions!E24*Assumptions!E47/30 -> 1333333.3 | F10: =Assumptions!F24*Assumptions!F47/30 -> 1333333.3 | G10: =Assumptions!G24*Assumptions!G47/30 -> 1333333.3 | H10: =Assumptions!H24*Assumptions!H47/30 -> 1333333.3 | I10: =Assumptions!I24*Assumptions!I47/30 -> 1333333.3 | ... AK10: =Assumptions!AK24*Assumptions!AK47/30 -> 28695000
A11: Total Current Assets | B11: =B9+B10 -> 6233333.3 | C11: =C9+C10 -> 5433333.3 | D11: =D9+D10 -> 4633333.3 | E11: =E9+E10 -> 4416666.7 | F11: =F9+F10 -> 4166666.7 | G11: =G9+G10 -> 3916666.7 | H11: =H9+H10 -> 3666666.7 | I11: =I9+I10 -> 3416666.7 | ... AK11: =AK9+AK10 -> 1.4131863e+08
A12: Equipment, Net Book Value (link from Depreciation) | B12: =Depreciation!B24 -> 2922222.2 | C12: =Depreciation!C24 -> 2844444.4 | D12: =Depreciation!D24 -> 2766666.7 | E12: =Depreciation!E24 -> 2688888.9 | F12: =Depreciation!F24 -> 2611111.1 | G12: =Depreciation!G24 -> 2533333.3 | H12: =Depreciation!H24 -> 2455555.6 | I12: =Depreciation!I24 -> 2377777.8 | ... AK12: =Depreciation!AK24 -> 950000
A13: Total Non-Current Assets | B13: =B12 -> 2922222.2 | C13: =C12 -> 2844444.4 | D13: =D12 -> 2766666.7 | E13: =E12 -> 2688888.9 | F13: =F12 -> 2611111.1 | G13: =G12 -> 2533333.3 | H13: =H12 -> 2455555.6 | I13: =I12 -> 2377777.8 | ... AK13: =AK12 -> 950000
A14: TOTAL ASSETS | B14: =B11+B13 -> 9155555.6 | C14: =C11+C13 -> 8277777.8 | D14: =D11+D13 -> 7400000 | E14: =E11+E13 -> 7105555.6 | F14: =F11+F13 -> 6777777.8 | G14: =G11+G13 -> 6450000 | H14: =H11+H13 -> 6122222.2 | I14: =I11+I13 -> 5794444.4 | ... AK14: =AK11+AK13 -> 1.4226863e+08
A16: LIABILITIES
A17: Accounts Payable (formula) = COGS × DPO ÷ 30 | B17: =Assumptions!B36*Assumptions!B48/30 -> 33333.333 | C17: =Assumptions!C36*Assumptions!C48/30 -> 33333.333 | D17: =Assumptions!D36*Assumptions!D48/30 -> 33333.333 | E17: =Assumptions!E36*Assumptions!E48/30 -> 66666.667 | F17: =Assumptions!F36*Assumptions!F48/30 -> 66666.667 | G17: =Assumptions!G36*Assumptions!G48/30 -> 66666.667 | H17: =Assumptions!H36*Assumptions!H48/30 -> 66666.667 | I17: =Assumptions!I36*Assumptions!I48/30 -> 66666.667 | ... AK17: =Assumptions!AK36*Assumptions!AK48/30 -> 1081500
A18: Loans Payable (input — no debt assumed) | B18: 0 | C18: 0 | D18: 0 | E18: 0 | F18: 0 | G18: 0 | H18: 0 | I18: 0 | J18: 0 | K18: 0 | L18: 0 | M18: 0 | N18: 0 | O18: 0 | P18: 0 | Q18: 0 | R18: 0 | S18: 0 | T18: 0 | U18: 0 | V18: 0 | W18: 0 | X18: 0 | Y18: 0 | Z18: 0 | AA18: 0 | AB18: 0 | AC18: 0 | AD18: 0 | AE18: 0 | AF18: 0 | AG18: 0 | AH18: 0 | AI18: 0 | AJ18: 0 | AK18: 0
A19: TOTAL LIABILITIES | B19: =B17+B18 -> 33333.333 | C19: =C17+C18 -> 33333.333 | D19: =D17+D18 -> 33333.333 | E19: =E17+E18 -> 66666.667 | F19: =F17+F18 -> 66666.667 | G19: =G17+G18 -> 66666.667 | H19: =H17+H18 -> 66666.667 | I19: =I17+I18 -> 66666.667 | ... AK19: =AK17+AK18 -> 1081500
A21: EQUITY
A22: Paid-in Capital — founder + seed investment, PKR (input) | B22: 10000000 | C22: 10000000 | D22: 10000000 | E22: 10000000 | F22: 10000000 | G22: 10000000 | H22: 10000000 | I22: 10000000 | J22: 10000000 | K22: 10000000 | L22: 10000000 | M22: 10000000 | N22: 10000000 | O22: 10000000 | P22: 10000000 | Q22: 10000000 | R22: 10000000 | S22: 10000000 | T22: 10000000 | U22: 10000000 | V22: 10000000 | W22: 10000000 | X22: 10000000 | Y22: 10000000 | Z22: 10000000 | AA22: 10000000 | AB22: 10000000 | AC22: 10000000 | AD22: 10000000 | AE22: 10000000 | AF22: 10000000 | AG22: 10000000 | AH22: 10000000 | AI22: 10000000 | AJ22: 10000000 | AK22: 10000000
A23: Retained Earnings (formula) = cumulative Net Profit | B23: ='Income Statement'!B22 -> -877777.78 | C23: =B23+'Income Statement'!C22 -> -1755555.6 | D23: =C23+'Income Statement'!D22 -> -2633333.3 | E23: =D23+'Income Statement'!E22 -> -2961111.1 | F23: =E23+'Income Statement'!F22 -> -3288888.9 | G23: =F23+'Income Statement'!G22 -> -3616666.7 | H23: =G23+'Income Statement'!H22 -> -3944444.4 | I23: =H23+'Income Statement'!I22 -> -4272222.2 | J23: =I23+'Income Statement'!J22 -> -4600000 | ... AK23: =AJ23+'Income Statement'!AK22 -> 1.3118713e+08
A24: TOTAL EQUITY | B24: =B22+B23 -> 9122222.2 | C24: =C22+C23 -> 8244444.4 | D24: =D22+D23 -> 7366666.7 | E24: =E22+E23 -> 7038888.9 | F24: =F22+F23 -> 6711111.1 | G24: =G22+G23 -> 6383333.3 | H24: =H22+H23 -> 6055555.6 | I24: =I22+I23 -> 5727777.8 | ... AK24: =AK22+AK23 -> 1.4118713e+08
A26: TOTAL LIABILITIES + EQUITY | B26: =B19+B24 -> 9155555.6 | C26: =C19+C24 -> 8277777.8 | D26: =D19+D24 -> 7400000 | E26: =E19+E24 -> 7105555.6 | F26: =F19+F24 -> 6777777.8 | G26: =G19+G24 -> 6450000 | H26: =H19+H24 -> 6122222.2 | I26: =I19+I24 -> 5794444.4 | ... AK26: =AK19+AK24 -> 1.4226863e+08
A27: Balance Check (Assets − Liab&Equity) — should be 0 once Cash is linked in Step 6 | B27: =B14-B26 -> 0 | C27: =C14-C26 -> 0 | D27: =D14-D26 -> 0 | E27: =E14-E26 -> 0 | F27: =F14-F26 -> 0 | G27: =G14-G26 -> 0 | H27: =H14-H26 -> 0 | I27: =I14-I26 -> 0 | ... AK27: =AK14-AK26 -> 0

Sheet Cashflow Statement
A1: ZulfiQode — Cashflow Statement (Step 6, indirect method)
A2: Starts from Net Profit, adjusts for non-cash items and working-capital changes, then tracks the cash balance.
A3: Legend: Green text = link to another tab | Black text = formula (same tab)
A5: Year | B5: 1 | C5: 1 | D5: 1 | E5: 1 | F5: 1 | G5: 1 | H5: 1 | I5: 1 | J5: 1 | K5: 1 | L5: 1 | M5: 1 | N5: 2 | O5: 2 | P5: 2 | Q5: 2 | R5: 2 | S5: 2 | T5: 2 | U5: 2 | V5: 2 | W5: 2 | X5: 2 | Y5: 2 | Z5: 3 | AA5: 3 | AB5: 3 | AC5: 3 | AD5: 3 | AE5: 3 | AF5: 3 | AG5: 3 | AH5: 3 | AI5: 3 | AJ5: 3 | AK5: 3
A6: Month # | B6: 1 | C6: 2 | D6: 3 | E6: 4 | F6: 5 | G6: 6 | H6: 7 | I6: 8 | J6: 9 | K6: 10 | L6: 11 | M6: 12 | N6: 13 | O6: 14 | P6: 15 | Q6: 16 | R6: 17 | S6: 18 | T6: 19 | U6: 20 | V6: 21 | W6: 22 | X6: 23 | Y6: 24 | Z6: 25 | AA6: 26 | AB6: 27 | AC6: 28 | AD6: 29 | AE6: 30 | AF6: 31 | AG6: 32 | AH6: 33 | AI6: 34 | AJ6: 35 | AK6: 36
A8: OPERATING ACTIVITIES
A9: Net Profit | B9: ='Income Statement'!B22 -> -877777.78 | C9: ='Income Statement'!C22 -> -877777.78 | D9: ='Income Statement'!D22 -> -877777.78 | E9: ='Income Statement'!E22 -> -327777.78 | F9: ='Income Statement'!F22 -> -327777.78 | G9: ='Income Statement'!G22 -> -327777.78 | H9: ='Income Statement'!H22 -> -327777.78 | I9: ='Income Statement'!I22 -> -327777.78 | ... AK9: ='Income Statement'!AK22 -> 14852352
A10: Add: Depreciation (non-cash) | B10: =Depreciation!B22 -> 77777.778 | C10: =Depreciation!C22 -> 77777.778 | D10: =Depreciation!D22 -> 77777.778 | E10: =Depreciation!E22 -> 77777.778 | F10: =Depreciation!F22 -> 77777.778 | G10: =Depreciation!G22 -> 77777.778 | H10: =Depreciation!H22 -> 77777.778 | I10: =Depreciation!I22 -> 77777.778 | ... AK10: =Depreciation!AK22 -> 119444.44
A11: Less: Increase in Accounts Receivable | B11: =-('Balance Sheet'!B10) -> -666666.67 | C11: =-('Balance Sheet'!C10-'Balance Sheet'!B10) -> 0 | D11: =-('Balance Sheet'!D10-'Balance Sheet'!C10) -> 0 | E11: =-('Balance Sheet'!E10-'Balance Sheet'!D10) -> -666666.67 | F11: =-('Balance Sheet'!F10-'Balance Sheet'!E10) -> 0 | G11: =-('Balance Sheet'!G10-'Balance Sheet'!F10) -> 0 | H11: =-('Balance Sheet'!H10-'Balance Sheet'!G10) -> 0 | I11: =-('Balance Sheet'!I10-'Balance Sheet'!H10) -> 0 | J11: =-('Balance Sheet'!J10-'Balance Sheet'!I10) -> 0 | ... AK11: =-('Balance Sheet'!AK10-'Balance Sheet'!AJ10) -> -945000
A12: Add: Increase in Accounts Payable | B12: ='Balance Sheet'!B17 -> 33333.333 | C12: ='Balance Sheet'!C17-'Balance Sheet'!B17 -> 0 | D12: ='Balance Sheet'!D17-'Balance Sheet'!C17 -> 0 | E12: ='Balance Sheet'!E17-'Balance Sheet'!D17 -> 33333.333 | F12: ='Balance Sheet'!F17-'Balance Sheet'!E17 -> 0 | G12: ='Balance Sheet'!G17-'Balance Sheet'!F17 -> 0 | H12: ='Balance Sheet'!H17-'Balance Sheet'!G17 -> 0 | I12: ='Balance Sheet'!I17-'Balance Sheet'!H17 -> 0 | J12: ='Balance Sheet'!J17-'Balance Sheet'!I17 -> 0 | ... AK12: ='Balance Sheet'!AK17-'Balance Sheet'!AJ17 -> 28000
A13: Net Cash from Operating Activities | B13: =SUM(B9:B12) -> -1433333.3 | C13: =SUM(C9:C12) -> -800000 | D13: =SUM(D9:D12) -> -800000 | E13: =SUM(E9:E12) -> -883333.33 | F13: =SUM(F9:F12) -> -250000 | G13: =SUM(G9:G12) -> -250000 | H13: =SUM(H9:H12) -> -250000 | I13: =SUM(I9:I12) -> -250000 | ... AK13: =SUM(AK9:AK12) -> 14054796
A15: INVESTING ACTIVITIES
A16: Purchase of Equipment (Capex) | B16: =-SUMPRODUCT((Depreciation!$B$6:$B$10=B6)*Depreciation!$C$6:$C$10) -> -3000000 | C16: =-SUMPRODUCT((Depreciation!$B$6:$B$10=C6)*Depreciation!$C$6:$C$10) -> 0 | D16: =-SUMPRODUCT((Depreciation!$B$6:$B$10=D6)*Depreciation!$C$6:$C$10) -> 0 | E16: =-SUMPRODUCT((Depreciation!$B$6:$B$10=E6)*Depreciation!$C$6:$C$10) -> 0 | F16: =-SUMPRODUCT((Depreciation!$B$6:$B$10=F6)*Depreciation!$C$6:$C$10) -> 0 | G16: =-SUMPRODUCT((Depreciation!$B$6:$B$10=G6)*Depreciation!$C$6:$C$10) -> 0 | H16: =-SUMPRODUCT((Depreciation!$B$6:$B$10=H6)*Depreciation!$C$6:$C$10) -> 0 | I16: =-SUMPRODUCT((Depreciation!$B$6:$B$10=I6)*Depreciation!$C$6:$C$10) -> 0 | ... AK16: =-SUMPRODUCT((Depreciation!$B$6:$B$10=AK6)*Depreciation!$C$6:$C$10) -> 0
A17: Net Cash from Investing Activities | B17: =B16 -> -3000000 | C17: =C16 -> 0 | D17: =D16 -> 0 | E17: =E16 -> 0 | F17: =F16 -> 0 | G17: =G16 -> 0 | H17: =H16 -> 0 | I17: =I16 -> 0 | ... AK17: =AK16 -> 0
A19: FINANCING ACTIVITIES
A20: Paid-in Capital raised this month | B20: ='Balance Sheet'!B22 -> 10000000 | C20: ='Balance Sheet'!C22-'Balance Sheet'!B22 -> 0 | D20: ='Balance Sheet'!D22-'Balance Sheet'!C22 -> 0 | E20: ='Balance Sheet'!E22-'Balance Sheet'!D22 -> 0 | F20: ='Balance Sheet'!F22-'Balance Sheet'!E22 -> 0 | G20: ='Balance Sheet'!G22-'Balance Sheet'!F22 -> 0 | H20: ='Balance Sheet'!H22-'Balance Sheet'!G22 -> 0 | I20: ='Balance Sheet'!I22-'Balance Sheet'!H22 -> 0 | J20: ='Balance Sheet'!J22-'Balance Sheet'!I22 -> 0 | ... AK20: ='Balance Sheet'!AK22-'Balance Sheet'!AJ22 -> 0
A21: Net Cash from Financing Activities | B21: =B20 -> 10000000 | C21: =C20 -> 0 | D21: =D20 -> 0 | E21: =E20 -> 0 | F21: =F20 -> 0 | G21: =G20 -> 0 | H21: =H20 -> 0 | I21: =I20 -> 0 | ... AK21: =AK20 -> 0
A23: Net Change in Cash | B23: =B13+B17+B21 -> 5566666.7 | C23: =C13+C17+C21 -> -800000 | D23: =D13+D17+D21 -> -800000 | E23: =E13+E17+E21 -> -883333.33 | F23: =F13+F17+F21 -> -250000 | G23: =G13+G17+G21 -> -250000 | H23: =H13+H17+H21 -> -250000 | I23: =I13+I17+I21 -> -250000 | ... AK23: =AK13+AK17+AK21 -> 14054796
A24: Beginning Cash | B24: 0 | C24: =B25 -> 5566666.7 | D24: =C25 -> 4766666.7 | E24: =D25 -> 3966666.7 | F24: =E25 -> 3083333.3 | G24: =F25 -> 2833333.3 | H24: =G25 -> 2583333.3 | I24: =H25 -> 2333333.3 | J24: =I25 -> 2083333.3 | ... AK24: =AJ25 -> 98568831
A25: Ending Cash | B25: =B24+B23 -> 5566666.7 | C25: =C24+C23 -> 4766666.7 | D25: =D24+D23 -> 3966666.7 | E25: =E24+E23 -> 3083333.3 | F25: =F24+F23 -> 2833333.3 | G25: =G24+G23 -> 2583333.3 | H25: =H24+H23 -> 2333333.3 | I25: =I24+I23 -> 2083333.3 | ... AK25: =AK24+AK23 -> 1.1262363e+08
